polars_astro/__init__.py
polars_astro/io/__init__.py
polars_astro/io/fits.py
polars_astro/np/__init__.py
polars_astro/np/np.py
polars_astro-0.2.2.dist-info/METADATA
polars_astro-0.2.2.dist-info/WHEEL
polars_astro-0.2.2.dist-info/licenses/LICENSE
polars_astro-0.2.2.dist-info/RECORD
