Metadata-Version: 2.4
Name: polars_astro
Version: 0.2.2
Summary: A package allowing simple interfacing with typical Astronomical data (FITS, numpy) in polars
Project-URL: Homepage, https://github.com/Sub6Resources/polars-astro
Project-URL: Issues, https://github.com/Sub6Resources/polars-astro/issues
Author-email: Matthew Whitaker <matthew.w3000@gmail.com>
License-File: LICENSE
Classifier: Operating System :: OS Independent
Classifier: Programming Language :: Python :: 3
Classifier: Topic :: Scientific/Engineering
Requires-Python: >=3.10
Requires-Dist: fitsio
Requires-Dist: numpy
Requires-Dist: polars
